[
  {
    "name": "Assassin's Creed® Mirage",
    "slug": "assassins-creed-mirage",
    "description": "Experience the story of Basim, a cunning street thief with nightmarish visions, seeking answers and justice as he navigates the bustling streets of ninth-century Baghdad. Through a mysterious, ancient organization known as the Hidden Ones, he will become a deadly Master Assassin and change his fate in ways he never could have imagined.",
    "excerpt": "Experience the story of Basim, a cunning street thief with nightmarish visions, seeking answers and justice as he navigates the bustling streets of ninth-century Baghdad. Through a mysterious, ancient organization known as the Hidden Ones, he will become a deadly Master Assassin and change his fate in ways he never could have imagined.",
    "price": 579000,
    "developer": "Ubisoft",
    "publisher": "Ubisoft",
    "platform": ["windows"],
    "genres": ["Action", "Adventure"],
    "thumbnail": "https://cdn2.unrealengine.com/epic-launch-logo-400x172-c0289bc57588.png?h=270&quality=medium&resize=1&w=480",
    "images": [
      "https://cdn2.unrealengine.com/breaker-image-1920x1080-1920x1080-9b4788ed14ab.png",
      "https://cdn2.unrealengine.com/bagdad-vista-final-3840x2160-053259da6873.jpg",
      "https://cdn2.unrealengine.com/air-assassination-ac1-gold1920x1080-1920x1080-cb3af9126f5c.jpg",
      "https://cdn2.unrealengine.com/bureau-concept-gold-candidate1920x1080-1920x1080-bf39631f989d.png",
      "https://cdn2.unrealengine.com/chocking-smoke-bomb-gold-rgb-1080p-1920x1080-cd8a2bb24a91.png"
    ],
    "createdAt": "2023-12-15T15:32:06.350Z",
    "updatedAt": "2024-03-18T14:47:12.101Z"
  }
]
